dathas/__init__.py
dathas/dathas.py
dathas/util.py
dathas-0.0.5.dist-info/LICENSE
dathas-0.0.5.dist-info/METADATA
dathas-0.0.5.dist-info/WHEEL
dathas-0.0.5.dist-info/top_level.txt
dathas-0.0.5.dist-info/RECORD
