Metadata-Version: 2.1
Name: dathas
Version: 0.0.5
Summary: Enhance your Python dataclasses
Home-page: https://github.com/zigai/dathas
Author: Ziga Ivansek
Author-email: ziga.ivansek@gmail.com
License: MIT
Platform: UNKNOWN
Classifier: Programming Language :: Python
Classifier: Programming Language :: Python :: 3.10
Classifier: Programming Language :: Python :: 3 :: Only
Classifier: Topic :: Software Development :: Libraries :: Python Modules
Requires-Python: >=3.10
License-File: LICENSE
